logger/__init__.py
py_master-0.0.1.dist-info/LICENSE
py_master-0.0.1.dist-info/METADATA
py_master-0.0.1.dist-info/WHEEL
py_master-0.0.1.dist-info/top_level.txt
py_master-0.0.1.dist-info/RECORD
