Metadata-Version: 2.1
Name: py-master
Version: 0.0.1
Summary: common package
Home-page: https://github.com/patrickxu1986/py_master
Author: patrickxu
Author-email: patrickxu@wiatec.com
License: UNKNOWN
Project-URL: Bug Tracker, https://github.com/patrickxu1986/py_master/issues
Platform: UNKNOWN
Classifier: Programming Language :: Python :: 3
Classifier: License :: OSI Approved :: MIT License
Classifier: Operating System :: OS Independent
Requires-Python: >=3.6
License-File: LICENSE
